[
	{
		"inputs": [],
		"stateMutability": "nonpayable",
		"type": "constructor"
	},
	{
		"anonymous": false,
		"inputs": [
			{
				"indexed": true,
				"internalType": "address",
				"name": "oldAdmin",
				"type": "address"
			},
			{
				"indexed": true,
				"internalType": "address",
				"name": "newAdmin",
				"type": "address"
			}
		],
		"name": "CharityAdminUpdated",
		"type": "event"
	},
	{
		"anonymous": false,
		"inputs": [
			{
				"indexed": false,
				"internalType": "address",
				"name": "sender",
				"type": "address"
			},
			{
				"indexed": false,
				"internalType": "uint256",
				"name": "amount",
				"type": "uint256"
			}
		],
		"name": "FundsReceived",
		"type": "event"
	},
	{
		"anonymous": false,
		"inputs": [
			{
				"indexed": true,
				"internalType": "uint256",
				"name": "proposalId",
				"type": "uint256"
			},
			{
				"indexed": false,
				"internalType": "address",
				"name": "destination",
				"type": "address"
			},
			{
				"indexed": false,
				"internalType": "uint256",
				"name": "amount",
				"type": "uint256"
			}
		],
		"name": "FundsReleased",
		"type": "event"
	},
	{
		"anonymous": false,
		"inputs": [
			{
				"indexed": true,
				"internalType": "address",
				"name": "oldPlatform",
				"type": "address"
			},
			{
				"indexed": true,
				"internalType": "address",
				"name": "newPlatform",
				"type": "address"
			}
		],
		"name": "PlatformUpdated",
		"type": "event"
	},
	{
		"anonymous": false,
		"inputs": [
			{
				"indexed": true,
				"internalType": "uint256",
				"name": "proposalId",
				"type": "uint256"
			},
			{
				"indexed": false,
				"internalType": "uint256",
				"name": "amount",
				"type": "uint256"
			},
			{
				"indexed": false,
				"internalType": "address",
				"name": "destination",
				"type": "address"
			}
		],
		"name": "ProposalCreated",
		"type": "event"
	},
	{
		"anonymous": false,
		"inputs": [
			{
				"indexed": true,
				"internalType": "uint256",
				"name": "proposalId",
				"type": "uint256"
			},
			{
				"indexed": false,
				"internalType": "enum ProjectWallet.ProposalStatus",
				"name": "status",
				"type": "uint8"
			}
		],
		"name": "ProposalStatusChanged",
		"type": "event"
	},
	{
		"inputs": [],
		"name": "charityAdmin",
		"outputs": [
			{
				"internalType": "address",
				"name": "",
				"type": "address"
			}
		],
		"stateMutability": "view",
		"type": "function"
	},
	{
		"inputs": [
			{
				"internalType": "string",
				"name": "description",
				"type": "string"
			},
			{
				"internalType": "string",
				"name": "evidenceIpfsHash",
				"type": "string"
			},
			{
				"internalType": "uint256",
				"name": "amount",
				"type": "uint256"
			},
			{
				"internalType": "address payable",
				"name": "destinationAccount",
				"type": "address"
			}
		],
		"name": "createProposal",
		"outputs": [
			{
				"internalType": "uint256",
				"name": "",
				"type": "uint256"
			}
		],
		"stateMutability": "nonpayable",
		"type": "function"
	},
	{
		"inputs": [
			{
				"internalType": "uint256",
				"name": "proposalId",
				"type": "uint256"
			}
		],
		"name": "executeProposal",
		"outputs": [],
		"stateMutability": "nonpayable",
		"type": "function"
	},
	{
		"inputs": [],
		"name": "getBalance",
		"outputs": [
			{
				"internalType": "uint256",
				"name": "",
				"type": "uint256"
			}
		],
		"stateMutability": "view",
		"type": "function"
	},
	{
		"inputs": [],
		"name": "getProposalCount",
		"outputs": [
			{
				"internalType": "uint256",
				"name": "",
				"type": "uint256"
			}
		],
		"stateMutability": "view",
		"type": "function"
	},
	{
		"inputs": [
			{
				"internalType": "address",
				"name": "_charityAdmin",
				"type": "address"
			},
			{
				"internalType": "uint256",
				"name": "_projectId",
				"type": "uint256"
			}
		],
		"name": "initialize",
		"outputs": [],
		"stateMutability": "nonpayable",
		"type": "function"
	},
	{
		"inputs": [],
		"name": "owner",
		"outputs": [
			{
				"internalType": "address",
				"name": "",
				"type": "address"
			}
		],
		"stateMutability": "view",
		"type": "function"
	},
	{
		"inputs": [],
		"name": "platform",
		"outputs": [
			{
				"internalType": "address",
				"name": "",
				"type": "address"
			}
		],
		"stateMutability": "view",
		"type": "function"
	},
	{
		"inputs": [],
		"name": "projectId",
		"outputs": [
			{
				"internalType": "uint256",
				"name": "",
				"type": "uint256"
			}
		],
		"stateMutability": "view",
		"type": "function"
	},
	{
		"inputs": [
			{
				"internalType": "uint256",
				"name": "",
				"type": "uint256"
			}
		],
		"name": "proposals",
		"outputs": [
			{
				"internalType": "uint256",
				"name": "id",
				"type": "uint256"
			},
			{
				"internalType": "string",
				"name": "description",
				"type": "string"
			},
			{
				"internalType": "string",
				"name": "evidenceIpfsHash",
				"type": "string"
			},
			{
				"internalType": "uint256",
				"name": "amount",
				"type": "uint256"
			},
			{
				"internalType": "address payable",
				"name": "destinationAccount",
				"type": "address"
			},
			{
				"internalType": "enum ProjectWallet.ProposalStatus",
				"name": "status",
				"type": "uint8"
			},
			{
				"internalType": "uint256",
				"name": "createdAt",
				"type": "uint256"
			},
			{
				"internalType": "uint256",
				"name": "executedAt",
				"type": "uint256"
			}
		],
		"stateMutability": "view",
		"type": "function"
	},
	{
		"inputs": [
			{
				"internalType": "address",
				"name": "newCharityAdmin",
				"type": "address"
			}
		],
		"name": "updateCharityAdmin",
		"outputs": [],
		"stateMutability": "nonpayable",
		"type": "function"
	},
	{
		"inputs": [
			{
				"internalType": "address",
				"name": "newPlatform",
				"type": "address"
			}
		],
		"name": "updatePlatform",
		"outputs": [],
		"stateMutability": "nonpayable",
		"type": "function"
	},
	{
		"inputs": [
			{
				"internalType": "uint256",
				"name": "proposalId",
				"type": "uint256"
			},
			{
				"internalType": "enum ProjectWallet.ProposalStatus",
				"name": "status",
				"type": "uint8"
			}
		],
		"name": "updateProposalStatus",
		"outputs": [],
		"stateMutability": "nonpayable",
		"type": "function"
	},
	{
		"stateMutability": "payable",
		"type": "receive"
	}
]